mtbls2mhd/__init__.py
mtbls2mhd/config.py
mtbls2mhd/convertor_factory.py
mtbls2mhd/commands/__init__.py
mtbls2mhd/commands/cli.py
mtbls2mhd/commands/create.py
mtbls2mhd/commands/create_mhd_file.py
mtbls2mhd/commands/validate.py
mtbls2mhd/v0_1/__init__.py
mtbls2mhd/v0_1/legacy/__init__.py
mtbls2mhd/v0_1/legacy/builder.py
mtbls2mhd/v0_1/legacy/convertor.py
mtbls2mhd/v0_1/legacy/db_metadata_collector.py
mtbls2mhd/v0_1/legacy/folder_metadata_collector.py
mtbls2mhd/v0_1/legacy/mtbls_study_schema.py
mtbls2mhd/v0_1/ms/__init__.py
mtbls2mhd/v0_1/ms/convertor.py
mtbls_mhd_integration-0.0.12.dist-info/licenses/LICENSE
mtbls_mhd_integration-0.0.12.dist-info/METADATA
mtbls_mhd_integration-0.0.12.dist-info/WHEEL
mtbls_mhd_integration-0.0.12.dist-info/entry_points.txt
mtbls_mhd_integration-0.0.12.dist-info/top_level.txt
mtbls_mhd_integration-0.0.12.dist-info/RECORD
