Metadata-Version: 2.4
Name: mtbls-mhd-integration
Version: 0.0.12
Summary: MetaboLights - MetabolomicsHub Integration
Author-email: MetaboLights Team <metabolights-help@ebi.ac.uk>
License-Expression: Apache-2.0
Requires-Python: <4.0,>=3.12
License-File: LICENSE
Requires-Dist: asyncpg>=0.30.0
Requires-Dist: metabolights-utils>=1.4.16
Requires-Dist: mhd-model>=0.1.41
Requires-Dist: psycopg[binary,pool]>=3.3.2
Requires-Dist: pydantic>=2.12.4
Requires-Dist: pydantic-settings>=2.10.1
Requires-Dist: pyyaml>=6.0.3
Requires-Dist: sqlalchemy>=2.0.41
Dynamic: license-file
